
[
    {
        "Card": "O Guru",
        "bg": "The-Guru.png",
        "Mantra": "É inútil, a não ser que eu possa usar.",
        "Palavras": "Ensino, Funcional, Prático, Habilidades, Aplicação de Ideias, Mentor, Mestre Espiritual, Pragmático, Pé no Chão, Direção, Uso do Conhecimento, Aplicação de Ideias"
    },
    {
        "Card": "A Bibliotecária",
        "bg": "The-Librarian.png",
        "Mantra": "Conhecimento é poder.",
        "Palavras": "Teoria, Livros, Informações, Dados, Aprendizagem, Estudo, Documentos, Localização de Livros, Armazenamento de Informações, Educação, Know-how, Compreenção, Concursos, Provas"
    },
    {
        "Card": "O Maestro",
        "bg": "The-Conductor.png",
        "Mantra": "Eu estou no controle. Eu sou o Rei/Rainha.",
        "Palavras": "Controle, Regular, Ordem, Direcionar, Piloto, Regra, Autoridade, Dominação, Manipular, Autonomia, Autodeteriminação, Autogoverno, Soberania, Liberade"
    },
    {
        "Card": "O Abridor de Caminhos",
        "bg": "The-Road-Opener.png",
        "Mantra": "A estrada à frente está desimpedida.",
        "Palavras": "Abertura, Banimento, Compensação, Remoção, Oportunidades, Dispersão, Sorte, Circunstâncias Favoráveis, Probabilidade de Sucesso Melhorada, Vantagem, Novas Direções, Prosperidade, Novo Foco"
    },
    {
        "Card": "O Protetor",
        "bg": "The-Protector.png",
        "Mantra": "Tudo está seguro, eu estou seguro.",
        "Palavras": "Proteção, Segurança, Garantia, Defesa, Proteger, Blindar, Salvaguardar, Acautelar, Manter Seguro, Fora de Perigo"
    },
    {
        "Card": "A Mãe",
        "bg": "The-Mother.png",
        "Mantra": "",
        "Palavras": ""
    },
    {
        "Card": "O Reparador",
        "bg": "The-Fixer.png"
    },
    {
        "Card": "A Ideia",
        "bg": "The-Idea.png"
    },
    {
        "Card": "O Pai",
        "bg": "The-Father.png"
    },
    {
        "Card": "A Dançarina",
        "bg": "The-Dancer.png"
    },
    {
        "Card": "O Sol",
        "bg": "The-Sun.png"
    },
    {
        "Card": "O Santo",
        "bg": "The-Saint.png"
    },
    {
        "Card": "O Olho",
        "bg": "The-Eye.png"
    },
    {
        "Card": "O Mestre",
        "bg": "The-Master.png"
    },
    {
        "Card": "O Diabo",
        "bg": "The-Devil.png"
    },
    {
        "Card": "A Vidente",
        "bg": "The-Seer.png"
    },
    {
        "Card": "A Bruxa",
        "bg": "The-Witch.png"
    },
    {
        "Card": "A Mídia",
        "bg": "The-Media.png"
    },
    {
        "Card": "O Explorador",
        "bg": "The-Explorer.png"
    },
    {
        "Card": "A Afortunada",
        "bg": "The-Fortunate.png"
    },
    {
        "Card": "O Levitador",
        "bg": "The-Levitator.png"
    },
    {
        "Card": "A Carnal",
        "bg": "The-Carnal.png"
    },
    {
        "Card": "O Planeta",
        "bg": "The-Planet.png"
    },
    {
        "Card": "A Adversário",
        "bg": "The-Opposer.png"
    },
    {
        "Card": "A Lua",
        "bg": "The-Moon.png"
    },
    {
        "Card": "A Desesperado",
        "bg": "The-Desperate.png"
    },
    {
        "Card": "A Casta",
        "bg": "The-Chaste.png"
    },
    {
        "Card": "O Monge",
        "bg": "The-Monk.png"
    },
    {
        "Card": "O Exaurido",
        "bg": "The-Depleted.png"
    },
    {
        "Card": "A Manifestante",
        "bg": "The-Protester.png"
    },
    {
        "Card": "O Guardião do Portal",
        "bg": "The-Gate-Keeper.png"
    },
    {
        "Card": "Os Enamorados",
        "bg": "The-Lover.png"
    },
    {
        "Card": "O Mensageiro",
        "bg": "The-Messenger.png"
    },
    {
        "Card": "A Morta",
        "bg": "The-Dead.png"
    },
    {
        "Card": "A Balanceadora",
        "bg": "The-Balancer.png"
    },
    {
        "Card": "O Contemplador",
        "bg": "The-Contemplator.png"
    },
    {
        "Card": "O Pensador",
        "bg": "The-Thinker.png"
    },
    {
        "Card": "A Curandeira",
        "bg": "The-Healer.png"
    },
    {
        "Card": "O Doador",
        "bg": "The-Giver.png"
    },
    {
        "Card": "A Aventureira",
        "bg": "The-Adventurer.png"
    }
]
